sharpcal/__init__.py
sharpcal/calibration.py
sharpcal/kernels.py
sharpcal/prediction.py
sharpcal/recal.py
sharpcal/scores.py
sharpcal-0.0.2.dist-info/LICENSE
sharpcal-0.0.2.dist-info/METADATA
sharpcal-0.0.2.dist-info/WHEEL
sharpcal-0.0.2.dist-info/top_level.txt
sharpcal-0.0.2.dist-info/RECORD
