Metadata-Version: 2.1
Name: sharpcal
Version: 0.0.2
Summary: Compute and plot calibration-sharpness diagrams.
Author: Muthu Chidambaram
License: MIT License
Project-URL: Homepage, https://github.com/2014mchidamb/reassessing-calibration
Classifier: Programming Language :: Python :: 3
Classifier: Operating System :: OS Independent
Requires-Python: >=3.7
License-File: LICENSE
Requires-Dist: numpy >=1.26.4
Requires-Dist: scipy >=1.12.0
Requires-Dist: matplotlib >=3.5.1
Requires-Dist: torch >=2.0.0
Requires-Dist: beartype >=0.18.5
